bokehlab/__init__.py
bokehlab/bokehlab_magic.py
bokehlab/config.py
bokehlab/fix_copy_paste.py
bokehlab/install_magic.py
bokehlab/palettes.py
bokehlab/parser.py
bokehlab-0.2.10.dist-info/LICENSE
bokehlab-0.2.10.dist-info/METADATA
bokehlab-0.2.10.dist-info/WHEEL
bokehlab-0.2.10.dist-info/top_level.txt
bokehlab-0.2.10.dist-info/RECORD
