Metadata-Version: 2.1
Name: bokehlab
Version: 0.2.10
Summary: Interactive plotting with familiar syntax in Jupyter notebooks.
Home-page: https://github.com/axil/bokehlab
Author: Lev Maximov
Author-email: lev.maximov@gmail.com
License: MIT License
Keywords: bokeh,jupyter,notebook,plot,interactive
Platform: UNKNOWN
Classifier: Programming Language :: Python :: 3
Classifier: License :: OSI Approved :: MIT License
Classifier: Operating System :: OS Independent
License-File: LICENSE
Requires-Dist: bokeh (<3)
Requires-Dist: jupyter-bokeh (<=3.0.4)
Requires-Dist: matplotlib
Requires-Dist: pyyaml
Requires-Dist: jupyter-bokeh
Requires-Dist: pandas
